{
	"type": {
		"value": "feed"
	},
	"entry": [{
		"type": {
			"value": "video"
		},
		"id": "yes_action",
		"title": "Yes Action",
		"summary": "",
		"content": {
			"src": "https://tv4.live/api/stream/jorgebalagani@gmail.com/878095/livetv.epg/yes.movies.action.il.m3u8",
			"type": "video/hls"
		},
		"media_group": [{
			"type": "image",
			"media_item": [{
				"type": "image",
				"key": "image_base",
				"src": "http://assets-production.applicaster.com/applicaster-employees/support_team/yona/GolTV/channel_images/yes_action.jpg"
			}]
		}]
	},{
		"type": {
			"value": "video"
		},
		"id": "yes_comedy",
		"title": "Yes Comedy",
		"summary": "",
		"content": {
			"src": "https://tv4.live/api/stream/jorgebalagani@gmail.com/878095/livetv.epg/yes.movies.comady.il.m3u8",
			"type": "video/hls"
		},
		"media_group": [{
			"type": "image",
			"media_item": [{
				"type": "image",
				"key": "image_base",
				"src": "http://assets-production.applicaster.com/applicaster-employees/support_team/yona/GolTV/channel_images/yes_comedy.jpg"
			}]
		}]
	},{
		"type": {
			"value": "video"
		},
		"id": "yes_drama",
		"title": "Yes Drama",
		"summary": "",
		"content": {
			"src": "https://tv4.live/api/stream/jorgebalagani@gmail.com/878095/livetv.epg/yes.movies.drama.il.m3u8",
			"type": "video/hls"
		},
		"media_group": [{
			"type": "image",
			"media_item": [{
				"type": "image",
				"key": "image_base",
				"src": "http://assets-production.applicaster.com/applicaster-employees/support_team/yona/GolTV/channel_images/yes_drama.jpg"
			}]
		}]
	},{
		"type": {
			"value": "video"
		},
		"id": "yes_kids",
		"title": "Yes Kids",
		"summary": "",
		"content": {
			"src": "https://tv4.live/api/stream/jorgebalagani@gmail.com/878095/livetv.epg/yes.movies.kids.il.m3u8",
			"type": "video/hls"
		},
		"media_group": [{
			"type": "image",
			"media_item": [{
				"type": "image",
				"key": "image_base",
				"src": "http://assets-production.applicaster.com/applicaster-employees/support_team/yona/GolTV/channel_images/yes_movies_kids.png"
			}]
		}]
	},{
		"type": {
			"value": "video"
		},
		"id": "hot_cinema1",
		"title": "HOT Cinema 1",
		"summary": "",
		"content": {
			"src": "https://tv4.live/api/stream/jorgebalagani@gmail.com/878095/livetv.epg/hot.cinema.1.il.m3u8",
			"type": "video/hls"
		},
		"media_group": [{
			"type": "image",
			"media_item": [{
				"type": "image",
				"key": "image_base",
				"src": "http://assets-production.applicaster.com/applicaster-employees/support_team/yona/GolTV/channel_images/hotaction.jpg"
			}]
		}]
	},{
		"type": {
			"value": "video"
		},
		"id": "hot_cinema2",
		"title": "HOT Cinema 2",
		"summary": "",
		"content": {
			"src": "https://tv4.live/api/stream/jorgebalagani@gmail.com/878095/livetv.epg/hot.cinema.2.il.m3u8",
			"type": "video/hls"
		},
		"media_group": [{
			"type": "image",
			"media_item": [{
				"type": "image",
				"key": "image_base",
				"src": "http://assets-production.applicaster.com/applicaster-employees/support_team/yona/GolTV/channel_images/hotaction.jpg"
			}]
		}]
	},{
		"type": {
			"value": "video"
		},
		"id": "hot_cinema3",
		"title": "HOT Cinema 3",
		"summary": "",
		"content": {
			"src": "https://tv4.live/api/stream/jorgebalagani@gmail.com/878095/livetv.epg/hot.cinema.3.il.m3u8",
			"type": "video/hls"
		},
		"media_group": [{
			"type": "image",
			"media_item": [{
				"type": "image",
				"key": "image_base",
				"src": "http://assets-production.applicaster.com/applicaster-employees/support_team/yona/GolTV/channel_images/hotaction.jpg"
			}]
		}]
	},{
		"type": {
			"value": "video"
		},
		"id": "hot_cinema4",
		"title": "HOT Cinema 4",
		"summary": "",
		"content": {
			"src": "https://tv4.live/api/stream/jorgebalagani@gmail.com/878095/livetv.epg/hot.cinema.4.il.m3u8",
			"type": "video/hls"
		},
		"media_group": [{
			"type": "image",
			"media_item": [{
				"type": "image",
				"key": "image_base",
				"src": "http://assets-production.applicaster.com/applicaster-employees/support_team/yona/GolTV/channel_images/hotaction.jpg"
			}]
		}]
	},{
		"type": {
			"value": "video"
		},
		"id": "starz cinema",
		"title": "Starz Cinema",
		"summary": "",
		"content": {
			"src": "https://tv4.live/api/stream/jorgebalagani@gmail.com/878095/livetv.epg/starz.cinema.eastern.us.m3u8",
			"type": "video/hls"
		},
		"media_group": [{
			"type": "image",
			"media_item": [{
				"type": "image",
				"key": "image_base",
				"src": "https://i.ytimg.com/vi/8XP7tX550FM/maxresdefault.jpg"
			}]
		}]
	},{
		"type": {
			"value": "video"
		},
		"id": "starz_comedy",
		"title": "Starz Comedy",
		"summary": "",
		"content": {
			"src": "https://tv4.live/api/stream/jorgebalagani@gmail.com/878095/livetv.epg/starz.comedy.eastern.us.m3u8",
			"type": "video/hls"
		},
		"media_group": [{
			"type": "image",
			"media_item": [{
				"type": "image",
				"key": "image_base",
				"src": "https://i.vimeocdn.com/video/473574756_1280x720.jpg"
			}]
		}]
	},{
		"type": {
			"value": "video"
		},
		"id": "starz_edge",
		"title": "Starz Edge",
		"summary": "",
		"content": {
			"src": "https://tv4.live/api/stream/jorgebalagani@gmail.com/878095/livetv.epg/starz.edge.eastern.us.m3u8",
			"type": "video/hls"
		},
		"media_group": [{
			"type": "image",
			"media_item": [{
				"type": "image",
				"key": "image_base",
				"src": "https://i.vimeocdn.com/video/473608829_1280x720.jpg"
			}]
		}]
	},{
		"type": {
			"value": "video"
		},
		"id": "starz_encore",
		"title": "Starz Encore",
		"summary": "",
		"content": {
			"src": "https://tv4.live/api/stream/jorgebalagani@gmail.com/878095/livetv.epg/starz.encore.eastern.us.m3u8",
			"type": "video/hls"
		},
		"media_group": [{
			"type": "image",
			"media_item": [{
				"type": "image",
				"key": "image_base",
				"src": "https://www.unblockitall.com/wp-content/uploads/2018/10/starz-encore-300x194.jpg"
			}]
		}]
	},{
		"type": {
			"value": "video"
		},
		"id": "sony_movie_channel",
		"title": "Sony Movie Channel",
		"summary": "",
		"content": {
			"src": "https://tv4.live/api/stream/jorgebalagani@gmail.com/878095/livetv.epg/sony.movie.channel.us.m3u8",
			"type": "video/hls"
		},
		"media_group": [{
			"type": "image",
			"media_item": [{
				"type": "image",
				"key": "image_base",
				"src": "https://upload.wikimedia.org/wikipedia/en/d/de/Sonymoviesuk.jpg"
			}]
		}]
	},{
		"type": {
			"value": "video"
		},
		"id": "mgm_us",
		"title": "MGM US",
		"summary": "",
		"content": {
			"src": "https://tv4.live/api/stream/jorgebalagani@gmail.com/878095/livetv.epg/mgm.usa.us.m3u8",
			"type": "video/hls"
		},
		"media_group": [{
			"type": "image",
			"media_item": [{
				"type": "image",
				"key": "image_base",
				"src": "https://static.hollywoodreporter.com/sites/default/files/2020/01/mgm_logo_-_h_-_2019-928x523.jpg"
			}]
		}]
	},{
		"type": {
			"value": "video"
		},
		"id": "hallmark_channel",
		"title": "Hallmark Channel",
		"summary": "",
		"content": {
			"src": "https://tv4.live/api/stream/jorgebalagani@gmail.com/878095/livetv.epg/hallmark.channel.eastern.us.m3u8",
			"type": "video/hls"
		},
		"media_group": [{
			"type": "image",
			"media_item": [{
				"type": "image",
				"key": "image_base",
				"src": "https://nitrocdn.com/tPmOtEiKDWAARLPbkNDMvQBJYLQuGGXp/assets/static/optimized/rev-cd2ff2c/wp-content/uploads/2018/05/2018-05-15_15-11-53-990x556.png"
			}]
		}]
	},{
		"type": {
			"value": "video"
		},
		"id": "hallmark_drama",
		"title": "Hallmark Drama",
		"summary": "",
		"content": {
			"src": "https://tv4.live/api/stream/jorgebalagani@gmail.com/878095/livetv.epg/hallmark.drama.us.m3u8",
			"type": "video/hls"
		},
		"media_group": [{
			"type": "image",
			"media_item": [{
				"type": "image",
				"key": "image_base",
				"src": "https://hallmark.brightspotcdn.com/dims4/default/34a991c/2147483647/strip/true/crop/853x448+0+0/resize/1200x630!/quality/90/?url=http%3A%2F%2Fhallmark-channel-brightspot.s3.amazonaws.com%2F32%2Fb0%2Fc3efe488a6f6152224adf464f152%2Fhp17-slide-hallmarkdrama-853x570-02-f.jpg"
			}]
		}]
	},{
		"type": {
			"value": "video"
		},
		"id": "hallmark_mysteries",
		"title": "Hallmark Mysteries",
		"summary": "",
		"content": {
			"src": "https://tv4.live/api/stream/jorgebalagani@gmail.com/878095/livetv.epg/hallmark.movies.mysteries.eastern.us.m3u8",
			"type": "video/hls"
		},
		"media_group": [{
			"type": "image",
			"media_item": [{
				"type": "image",
				"key": "image_base",
				"src": "https://media.soapoperanetwork.com/2014/12/hallmark_moviesandmysteries_01_640x400.jpg"
			}]
		}]
	},{
		"type": {
			"value": "video"
		},
		"id": "hot_bollywood",
		"title": "HOT Bollywood",
		"summary": "",
		"content": {
			"src": "https://tv4.live/api/stream/jorgebalagani@gmail.com/878095/livetv.epg/hotbollywood.il.m3u8",
			"type": "video/hls"
		},
		"media_group": [{
			"type": "image",
			"media_item": [{
				"type": "image",
				"key": "image_base",
				"src": "https://lh3.googleusercontent.com/proxy/mdIp2HHv1sJ9XtoHr5_4NTraVdfvc36jNnoeWlSskLrWbjiWl2GBbPpvnNka3duk0SBZB0mkkcwVQIdQMJ9W-VZFZW8USaAIgK3pF1M6WCdc8XyydMeOjQ"
			}]
		}]
	},{
		"type": {
			"value": "video"
		},
		"id": "hot_bombay",
		"title": "HOT Bombay",
		"summary": "",
		"content": {
			"src": "https://tv4.live/api/stream/jorgebalagani@gmail.com/878095/livetv.epg/hotbombay.il.m3u8",
			"type": "video/hls"
		},
		"media_group": [{
			"type": "image",
			"media_item": [{
				"type": "image",
				"key": "image_base",
				"src": "https://media.tv4.live/hotbombay.il.png"
			}]
		}]
	}],
	"author": {
		"name": "Juan José"
	},
	"id": "GolTV_Movies",
	"title": "Movies"
}
